cfaTraceabilityModules/__init__.py
cfaTraceabilityModules/modules.py
cfaTraceabilityModules-0.0.1.dist-info/LICENCE
cfaTraceabilityModules-0.0.1.dist-info/METADATA
cfaTraceabilityModules-0.0.1.dist-info/WHEEL
cfaTraceabilityModules-0.0.1.dist-info/top_level.txt
cfaTraceabilityModules-0.0.1.dist-info/RECORD
