Metadata-Version: 2.1
Name: cfaTraceabilityModules
Version: 0.0.1
Summary: Chick-fil-A Traceability Modules
Home-page: https://github.com/pypa/sampleproject
Author: Omolewa Adaramola
Author-email: omolewa.adaramola@accesscfa.com
License: UNKNOWN
Platform: UNKNOWN
Classifier: Programming Language :: Python :: 3
Classifier: License :: OSI Approved :: MIT License
Classifier: Operating System :: OS Independent
Requires-Python: >=3.6
